{
  "manifest_version": 1,
  "scenario_id": "example_medium_0001",
  "split": "train",
  "generation_seed": 0,
  "map_id": "multi_robot_scenario_v1",
  "num_agents": 5,
  "robot_radius_m": 0.22,
  "free_area_m2": null,
  "nominal_speed_mps": 0.5,
  "conflict_distance_m": 0.9,
  "conflict_horizon_s": 8.0,
  "density_level": "medium",
  "spatial_density": null,
  "interaction_density": null,
  "conflict_edge_count": null,
  "max_conflict_degree": null,
  "mean_conflict_degree": null,
  "earliest_conflict_time_s": null,
  "simultaneous_conflict_count": null,
  "min_start_clearance_m": null,
  "min_goal_clearance_m": null,
  "min_path_separation_m": null,
  "bottleneck_ratio": null,
  "agents": {
    "r1": {"start": [0.0, 0.0], "goal": [1.0, 0.0]},
    "r2": {"start": [1.0, 1.0], "goal": [0.0, 1.0]},
    "r3": {"start": [-1.0, 0.0], "goal": [-1.0, 1.0]},
    "r4": {"start": [2.0, 0.0], "goal": [2.0, 1.0]},
    "r5": {"start": [0.0, 2.0], "goal": [1.0, 2.0]}
  },
  "conflict_edges": [],
  "generator_commit": null,
  "notes": "Example schema only; null metrics must be populated before use."
}
